tests/__init__.py
tests/context.py
tests/test_tracker.py
tracker/__init__.py
tracker/tracker.py
beat_tracker_wrapper-0.0.1.dist-info/LICENSE
beat_tracker_wrapper-0.0.1.dist-info/METADATA
beat_tracker_wrapper-0.0.1.dist-info/WHEEL
beat_tracker_wrapper-0.0.1.dist-info/top_level.txt
beat_tracker_wrapper-0.0.1.dist-info/RECORD
