Metadata-Version: 2.1
Name: beat-tracker-wrapper
Version: 0.0.1
Summary: This is a simple wrapper library for beat and down-beat tracking algorithm.
Home-page: https://github.com/SoloLa-Platform/madmom-docker
Author: ykhorizon
Author-email: ykhorizon@example.com
License: UNKNOWN
Platform: UNKNOWN
Classifier: Programming Language :: Python :: 3
Classifier: License :: OSI Approved :: MIT License
Classifier: Operating System :: OS Independent
Requires-Python: >=3.6
